beam/__init__.py
beam/__main__.py
beam/cli/__init__.py
beam/cli/configure.py
beam/cli/example.py
beam/cli/login.py
beam/cli/logs.py
beam/cli/main.py
beam/cli/quickstart.py
beam/cli/utils.py
beam/client/__init__.py
beam/client/client.py
beam/integrations.py
beam_client-0.2.189.dist-info/METADATA
beam_client-0.2.189.dist-info/WHEEL
beam_client-0.2.189.dist-info/entry_points.txt
beam_client-0.2.189.dist-info/RECORD
