Metadata-Version: 2.3
Name: beam-client
Version: 0.2.189
Summary: 
Author: beam.cloud
Author-email: support@beam.cloud
Requires-Python: >=3.8,<4.0
Classifier: Programming Language :: Python :: 3
Classifier: Programming Language :: Python :: 3.8
Classifier: Programming Language :: Python :: 3.9
Classifier: Programming Language :: Python :: 3.10
Classifier: Programming Language :: Python :: 3.11
Classifier: Programming Language :: Python :: 3.12
Classifier: Programming Language :: Python :: 3.13
Requires-Dist: beta9 (>=0.1.242,<0.2.0)
Requires-Dist: requests (>=2.31.0,<3.0.0)
Requires-Dist: websockets (>=13.0,<14.0)
